setup.py
crypto_exchanges.egg-info/PKG-INFO
crypto_exchanges.egg-info/SOURCES.txt
crypto_exchanges.egg-info/dependency_links.txt
crypto_exchanges.egg-info/not-zip-safe
crypto_exchanges.egg-info/top_level.txt
cryptoex/__init__.py
cryptoex/bittrex.py
cryptoex/poloniex.py