Metadata-Version: 1.2
Name: crypto-exchanges
Version: 0.0.0.1.dev0
Summary: Simple API wrappers for the exchange APIs
Home-page: http://github.com/nathbo/cryptoexchanges
Author: Nathanael Bosch
Author-email: nathanael.bosch@gmail.com
License: MIT
Platform: UNKNOWN
Requires-Python: >=3
